{
  "data": [
    {
      "symbol": "VIC",
      "companyName": "VIC",
      "price": 197.0,
      "change": -10.0,
      "changePercent": -4.83,
      "volume": 1804700
    },
    {
      "symbol": "VRE",
      "companyName": "VRE",
      "price": 29.95,
      "change": -1.25,
      "changePercent": -4.01,
      "volume": 2699600
    },
    {
      "symbol": "VHM",
      "companyName": "VHM",
      "price": 146.2,
      "change": -5.8,
      "changePercent": -3.82,
      "volume": 2362700
    },
    {
      "symbol": "ACB",
      "companyName": "ACB",
      "price": 25.4,
      "change": -0.75,
      "changePercent": -2.87,
      "volume": 19444000
    },
    {
      "symbol": "BVH",
      "companyName": "BVH",
      "price": 67.9,
      "change": -1.8,
      "changePercent": -2.58,
      "volume": 136400
    },
    {
      "symbol": "FPT",
      "companyName": "FPT",
      "price": 73.4,
      "change": -1.6,
      "changePercent": -2.13,
      "volume": 6416800
    },
    {
      "symbol": "SAB",
      "companyName": "SAB",
      "price": 46.8,
      "change": -1.0,
      "changePercent": -2.09,
      "volume": 467300
    },
    {
      "symbol": "VPB",
      "companyName": "VPB",
      "price": 25.95,
      "change": -0.5,
      "changePercent": -1.89,
      "volume": 7735300
    },
    {
      "symbol": "TPB",
      "companyName": "TPB",
      "price": 15.9,
      "change": -0.3,
      "changePercent": -1.85,
      "volume": 7973600
    },
    {
      "symbol": "SSI",
      "companyName": "SSI",
      "price": 26.55,
      "change": -0.45,
      "changePercent": -1.67,
      "volume": 12199400
    }
  ],
  "crawledAt": "2026-06-08T06:29:45.620657"
}