{
  "data": [
    {
      "symbol": "STB",
      "companyName": "STB",
      "price": 76.8,
      "change": 4.6,
      "changePercent": 6.37,
      "volume": 6934600
    },
    {
      "symbol": "VRE",
      "companyName": "VRE",
      "price": 35.45,
      "change": 1.85,
      "changePercent": 5.51,
      "volume": 12470600
    },
    {
      "symbol": "BVH",
      "companyName": "BVH",
      "price": 66.6,
      "change": 2.9,
      "changePercent": 4.55,
      "volume": 1034000
    },
    {
      "symbol": "GAS",
      "companyName": "GAS",
      "price": 76.5,
      "change": 2.9,
      "changePercent": 3.94,
      "volume": 1557500
    },
    {
      "symbol": "PLX",
      "companyName": "PLX",
      "price": 37.8,
      "change": 1.0,
      "changePercent": 2.72,
      "volume": 1738800
    },
    {
      "symbol": "HDB",
      "companyName": "HDB",
      "price": 27.35,
      "change": 0.45,
      "changePercent": 1.67,
      "volume": 12280300
    },
    {
      "symbol": "FPT",
      "companyName": "FPT",
      "price": 70.6,
      "change": 0.6,
      "changePercent": 0.86,
      "volume": 8533300
    },
    {
      "symbol": "TPB",
      "companyName": "TPB",
      "price": 15.8,
      "change": 0.05,
      "changePercent": 0.32,
      "volume": 11282100
    },
    {
      "symbol": "MSN",
      "companyName": "MSN",
      "price": 77.7,
      "change": 0.2,
      "changePercent": 0.26,
      "volume": 6062900
    },
    {
      "symbol": "VPB",
      "companyName": "VPB",
      "price": 27.85,
      "change": 0.05,
      "changePercent": 0.18,
      "volume": 14565400
    }
  ],
  "crawledAt": "2026-05-12T08:13:53.664975"
}